gitlock/__init__.py
gitlock/encryption_utils.py
gitlock/gitlock.py
gitlock-0.1.0.dist-info/licenses/LICENSE
gitlock-0.1.0.dist-info/METADATA
gitlock-0.1.0.dist-info/WHEEL
gitlock-0.1.0.dist-info/entry_points.txt
gitlock-0.1.0.dist-info/top_level.txt
gitlock-0.1.0.dist-info/RECORD
